setup.py
util/xrunner
xrunner/__init__.py
xrunner/__main__.py
xrunner/comparator.py
xrunner/comparator_test.py
xrunner/conf.py
xrunner/dial.py
xrunner/dial_test.py
xrunner/parser.py
xrunner/settings.py
xrunner/test.py
xrunner/test_test.py
xrunner/validator.py
xrunner/validator_test.py
xrunner/xrunner.py
xrunner.egg-info/PKG-INFO
xrunner.egg-info/SOURCES.txt
xrunner.egg-info/dependency_links.txt
xrunner.egg-info/requires.txt
xrunner.egg-info/top_level.txt