Metadata-Version: 1.1
Name: xrunner
Version: 0.1.1
Summary: Python RESTful API Testing & Microbenchmarking Tool for xml
Home-page: UNKNOWN
Author: Ujjwal Kanth
Author-email: ujjwal.kanth@unbxd.com
License: UNKNOWN
Keywords: rest,web,http,testing,xml
Platform: UNKNOWN
Classifier: Environment :: Console
Classifier: Natural Language :: English
Classifier: Programming Language :: Python :: 2.6
Classifier: Programming Language :: Python :: 2.7
Classifier: Topic :: Software Development :: Testing
Classifier: Topic :: Software Development :: Quality Assurance
Classifier: Topic :: Utilities
